nombretorraro/__init__.py
nombretorraro/esesto.py
nombretorraro-0.0.2.dist-info/METADATA
nombretorraro-0.0.2.dist-info/WHEEL
nombretorraro-0.0.2.dist-info/licenses/LICENSE
nombretorraro-0.0.2.dist-info/RECORD
