Metadata-Version: 2.1
Name: nombretorraro
Version: 0.0.2
Project-URL: Homepage, https://github.com/LLBF/Proyecto_libreria_DS
Author: TheBridge9-22
License-File: LICENSE
Classifier: License :: OSI Approved :: MIT License
Classifier: Programming Language :: Python :: 3
Requires-Python: >=3.7
